{
    "basic_info": {
      "description_header": "Software Developer",
      "description": "I am DeShon Dixon. US Army Veteran transitioning into software development. The transition into Software development has been hard but the life I've lived has been harder. I have chosen to transition into software development because I wanted a career where my work is meaningful and I can see the results of my hard work. I have struggled financially my whole life and it has fueled my drive throughout this transition. I know a career in software development would allow me to break the cycle and elevate me to a better position in life. I'm tired of just being another body at a job and easily expendable. Switching to a career in software development is my first time doing something I want to do in life. I've had nothing but dead end jobs other than the military. The military was a stepping stone for me to get out of the position I was in life and give me a chance I would've never otherwise had. The experience I've gained while in the military has instilled the ability to adapt in self-starting and collaborative environments.",
      "section_name": {
        "about": "About me",
        "projects": "Projects",
        "skills": "Skills",
        "experience": "Experience"
      }
    },
    "projects": [
      {
        "title": "Pigs and Bulls",
        "startDate": "2022",
        "description": "A word-guessing game (similar to wordle) in which you guess a 5-letter word; it tells you how many letters are correct (pigs) and how many words are correct and in the right spot (bulls).",
        "images": [
          "images/portfolio/animal-shelter/12.png",
          "images/portfolio/animal-shelter/13.png"
        ],
        "url": "https://thewordgame.github.io/pigs-and-bulls/",
        "technologies": [
          {
            "class": "devicon-html5-plain",
            "name": "HTML 5"
          },
          {
            "class": "devicon-javascript-plain",
            "name": "JavaScript"
          },
          {
            "class": "devicon-css3-plain",
            "name": "CSS 3"
          }
        ]
      },
      {
        "title": "Gallery of Horns",
        "startDate": "2022",
        "description": "User can view gallery of horned animals as well as 🖤 their favorite ones. There is also a drop down menu that allows the user to search by the amount of horns an animal has to narrow down their search.",
        "images": [
          "images/portfolio/photography/15.png",
          "images/portfolio/photography/16.png",
          "images/portfolio/photography/17.png",
          "images/portfolio/photography/18.png"
        ],
        "url": "https://galleryofhornsdd.netlify.app",
        "technologies": [
          {
            "class": "devicon-react-plain",
            "name": "React"
          },
          {
            "class": "devicon-javascript-plain",
            "name": "JavaScript"
          },
          {
          "class": "devicon-css3-plain",
          "name": "CSS 3"
          }
        ]
      },
      {
        "title": "Salmon Cookies",
        "startDate": "2022",
        "description": "A proof of concept application to calculate the number of cookies each location must make every day so that it can manage its supplies inventory and baking schedule. ",
        "images": [
          "images/portfolio/adventure/20.png",
          "images/portfolio/adventure/21.png"
        ],
        "url": "https://deshondixon.github.io/cookie-stand/",
        "technologies": [
          {
            "class": "devicon-html5-plain",
            "name": "HTML 5"
          },
          {
            "class": "devicon-javascript-plain",
            "name": "JavaScript"
          },
          {
          "class": "devicon-css3-plain",
          "name": "CSS 3"
          }
        ]
      }
    ],
    "experience": [
      {
        "company": "United States Army",
        "title": "91B Wheeled Vehicle Mechanic",
        "years": "11/22/2016 - 11/27/2019",
        "mainTech": [
          "11/22/2016 - 11/27/2019"
        ],
        "technologies": [
          "",
          "",
          "",
          "",
          "",
          "",
          ""
        ]
      },
      {
        "company": "Code Fellows",
        "title": "Software Developer",
        "years": "10.2022 - present",
        "mainTech": [
          "Python 10/8/22"
        ],
        "technologies": [
          "REST API",
          "JavaScript",
          "Bootstrap",
          "HTML5",
          "CSS3",
          "Python",
          "React"
        ]
      }
    ]
  }
